cyberark_tpc_plugin_parser-0.3.1.dist-info/licenses/LICENSE
tpc_plugin_parser/__init__..py
tpc_plugin_parser/parser.py
tpc_plugin_parser/lexer/__init__.py
tpc_plugin_parser/lexer/lexer.py
tpc_plugin_parser/lexer/tokens/__init__.py
tpc_plugin_parser/lexer/tokens/assignment.py
tpc_plugin_parser/lexer/tokens/comment.py
tpc_plugin_parser/lexer/tokens/cpm_parameter_validation.py
tpc_plugin_parser/lexer/tokens/fail_state.py
tpc_plugin_parser/lexer/tokens/parse_error.py
tpc_plugin_parser/lexer/tokens/section_header.py
tpc_plugin_parser/lexer/tokens/transition.py
tpc_plugin_parser/lexer/utilities/__init__.py
tpc_plugin_parser/lexer/utilities/regex.py
tpc_plugin_parser/lexer/utilities/token_name.py
tpc_plugin_parser/lexer/utilities/types.py
cyberark_tpc_plugin_parser-0.3.1.dist-info/METADATA
cyberark_tpc_plugin_parser-0.3.1.dist-info/WHEEL
cyberark_tpc_plugin_parser-0.3.1.dist-info/top_level.txt
cyberark_tpc_plugin_parser-0.3.1.dist-info/RECORD
