Metadata-Version: 2.4
Name: cyberark-tpc-plugin-parser
Version: 0.3.1
Summary: A package to help parse CyberArk TPC plugin prompts and process files.
Author-email: Peter McDonald <git@petermcdonald.co.uk>
License: MIT License
Project-URL: homepage, https://github.com/petermcd/CyberArk-TPC-Plugin-Parser
Project-URL: repository, https://github.com/petermcd/CyberArk-TPC-Plugin-Parser.git
Project-URL: issues, https://github.com/petermcd/CyberArk-TPC-Plugin-Parser/issues
Keywords: cyberark,parser,tpc
Classifier: Intended Audience :: Developers
Classifier: Programming Language :: Python
Classifier: Programming Language :: Python :: 3.11
Classifier: Programming Language :: Python :: 3.12
Classifier: Programming Language :: Python :: 3.13
Classifier: Programming Language :: Python :: 3.14
Classifier: Programming Language :: Python :: 3.15
Classifier: Topic :: Software Development :: Testing
Classifier: Typing :: Typed
Requires-Python: >=3.11
License-File: LICENSE
Dynamic: license-file
